PrometheusInterface/PrometheusInterface.pdf
PrometheusInterface/__init__.py
PrometheusInterface/prometheus_interface.py
robotframework_prometheus-0.8.0.dist-info/METADATA
robotframework_prometheus-0.8.0.dist-info/WHEEL
robotframework_prometheus-0.8.0.dist-info/top_level.txt
robotframework_prometheus-0.8.0.dist-info/RECORD
