Metadata-Version: 2.1
Name: robotframework-prometheus
Version: 0.8.0
Summary: Additional Robot Framework keywords
Home-page: https://github.com/test-fullautomation/robotframework-prometheus
Author: Holger Queckenstedt
Author-email: Holger.Queckenstedt@de.bosch.com
License: UNKNOWN
Platform: UNKNOWN
Classifier: Programming Language :: Python :: 3
Classifier: License :: OSI Approved :: Apache Software License
Classifier: Operating System :: OS Independent
Classifier: Development Status :: 4 - Beta
Classifier: Intended Audience :: Developers
Classifier: Topic :: Software Development
Requires-Python: >=3.0
Requires-Dist: PythonExtensionsCollection
Requires-Dist: robotframework
Requires-Dist: prometheus-client
